[
	{"id":114,"date":"2014-08-11","employee":"Sudie V. Goldsmith","customer":"Stephen H. Peachey","status":"new","fee":63,"taxes":12,"total":1522,"shipping_company":"Shipping B","payment_method":"Wire Transfer"},
	{"id":115,"date":"2014-08-11","employee":"Sherley D. Berryman","customer":"Sabrina N. Hermann","status":"ready","fee":78,"taxes":45,"total":1788,"shipping_company":"Shipping A","payment_method":"Wire Transfer"},
	{"id":116,"date":"2014-08-11","employee":"Ray M. Parra","customer":"Regine H.Field","status":"ready","fee":14,"taxes":4,"total":988,"shipping_company":"Shipping A","payment_method":"Cash"},
	{"id":117,"date":"2014-08-11","employee":"Romaine B. Alley","customer":"Stephane A. Chandler","status":"completed","fee":0,"taxes":0,"total":0,"shipping_company":"Shipping C","payment_method":"Credit Card"},
	{"id":118,"date":"2014-08-11","employee":"Jamila N. Mccallister","customer":"Olimpia C. Whelan","status":"new","fee":55,"taxes":13,"total":2100,"shipping_company":"Shipping E","payment_method":"Credit Card"},
	{"id":119,"date":"2014-08-11","employee":"Romaine B. Alley","customer":"Jettie P. Whelan","status":"ready","fee":18,"taxes":8,"total":956,"shipping_company":"Shipping A","payment_method":"Wire Transfer"},
	{"id":120,"date":"2014-08-11","employee":"Lane E. Dion","customer":"Stepanie P. Lilley","status":"completed","fee":133,"taxes":33,"total":754,"shipping_company":"Shipping D", "payment_method":"Cash"},
	{"id":1113,"date":"2014-08-11","employee":"Jolie P. Sparks","customer":"Bradly N. Mauro","status":"new","fee":13,"taxes":1,"total":255,"shipping_company":"Shipping A","payment_method":"Cash"},
	{"id":1114,"date":"2014-08-11","employee":"Sudie V. Goldsmith","customer":"Stephen H. Peachey","status":"new","fee":63,"taxes":12,"total":1522,"shipping_company":"Shipping B","payment_method":"Wire Transfer"},
	{"id":1115,"date":"2014-08-11","employee":"Sherley D. Berryman","customer":"Sabrina N. Hermann","status":"ready","fee":78,"taxes":45,"total":1788,"shipping_company":"Shipping A","payment_method":"Wire Transfer"},
	{"id":1116,"date":"2014-08-11","employee":"Ray M. Parra","customer":"Regine H.Field","status":"ready","fee":14,"taxes":4,"total":988,"shipping_company":"Shipping A","payment_method":"Cash"},
	{"id":1117,"date":"2014-08-11","employee":"Romaine B. Alley","customer":"Stephane A. Chandler","status":"completed","fee":0,"taxes":0,"total":0,"shipping_company":"Shipping C","payment_method":"Credit Card"},
	{"id":1118,"date":"2014-08-11","employee":"Jamila N. Mccallister","customer":"Olimpia C. Whelan","status":"new","fee":55,"taxes":13,"total":2100,"shipping_company":"Shipping E","payment_method":"Credit Card"},
	{"id":1119,"date":"2014-08-11","employee":"Romaine B. Alley","customer":"Jettie P. Whelan","status":"ready","fee":18,"taxes":8,"total":956,"shipping_company":"Shipping A","payment_method":"Wire Transfer"},
	{"id":1120,"date":"2014-08-11","employee":"Lane E. Dion","customer":"Stepanie P. Lilley","status":"completed","fee":133,"taxes":33,"total":754,"shipping_company":"Shipping D", "payment_method":"Cash"}
]